gqlppy/__init__.py
gqlppy/__main__.py
gqlppy/gql-earley.lark
gqlppy/gql-lalr.lark
gqlppy/parser.py
gqlppy-0.6.0.dist-info/licenses/LICENSE
gqlppy-0.6.0.dist-info/METADATA
gqlppy-0.6.0.dist-info/WHEEL
gqlppy-0.6.0.dist-info/top_level.txt
gqlppy-0.6.0.dist-info/RECORD
